LICENSE
README.rst
requirements.txt
setup.cfg
setup.py
test-requirements.txt
tox.ini
cachetclient/__init__.py
cachetclient/cachet.py
cachetclient/client.py
cachetclient/exceptions.py
contrib/example.py
contrib/sensu-cachet.py
python_cachetclient.egg-info/PKG-INFO
python_cachetclient.egg-info/SOURCES.txt
python_cachetclient.egg-info/dependency_links.txt
python_cachetclient.egg-info/not-zip-safe
python_cachetclient.egg-info/pbr.json
python_cachetclient.egg-info/requires.txt
python_cachetclient.egg-info/top_level.txt