Metadata-Version: 1.1
Name: python-cachetclient
Version: 0.2.5
Summary: A client and library for the Cachet administrative interface
Home-page: https://github.com/dmsimard/python-cachetclient
Author: David Moreau Simard
Author-email: dms@redhat.com
License: UNKNOWN
Platform: UNKNOWN
Classifier: License :: OSI Approved :: Apache Software License
Classifier: Development Status :: 4 - Beta
Classifier: Intended Audience :: Developers
Classifier: Intended Audience :: System Administrators
Classifier: Intended Audience :: Information Technology
Classifier: Programming Language :: Python :: 2.7
Classifier: Topic :: Utilities
